{    
    "id": 124222625,
    "name": "boss of pinecones",
    "author": "pilka2",
    "creators": ["pilka2"],
    "verifier": "pilka2",
    "verification": "https://youtu.be/ESzsvrpW0Jo?si=0X1GmbEuyfDyF6ha",
    "percentToQualify": "100",
    "password": "Open",
    "records": [
        {
            "user": "liquidman6776",
            "link": "https://medal.tv/games/geometry-dash/clips/kQnjFGAicZzzL8iO6?invite=cr-MSxNTUosNDExNTgzNjMy&v=21",
            "percent": 100,
            "hz": 360
        }
    ]
} 
