{
    "id": 124398923,
    "name": "po from panding 2",
    "author": "quantumrootbeer",
    "creators": ["quantumrootbeer"],
    "verifier": "quantumrootbeer",
    "verification": "https://www.youtube.com/watch?v=VLxv3o-KRfs",
    "percentToQualify": "100",
    "password": "open",
    "records": [
        {
            "user": "GD Bean",
            "link": "https://youtu.be/S7cbJDDYpI8",
            "percent": 100,
            "hz": 360
        },
        {
            "user": "Ant_Gam3R",
            "link": "https://medal.tv/games/geometry-dash/clips/kRKqi73FevjEhBNTt?invite=cr-MSxBV3ksNDIwNjgwOTY3",
            "percent": 100,
            "hz": 240
        },
        {
            "user": "Liquidman6776",
            "link": "https://medal.tv/games/geometry-dash/clips/kU36pqEXzNnybAgYH?invite=cr-MSxYZm4sNDIwNjgwOTY3",
            "percent": 100,
            "hz": 360
        },
        {
            "user": "GamerAJG2012",
            "link": "https://youtu.be/5jE45IDuVzk",
            "percent": 100,
            "hz": 144
        }
    ]
}
